secretcrypt/__init__.py
secretcrypt/base_aes.py
secretcrypt/decrypt_secret.py
secretcrypt/encrypt_secret.py
secretcrypt/kms.py
secretcrypt/local.py
secretcrypt/mock_crypter.py
secretcrypt/password.py
secretcrypt/plain.py
secretcrypt-1.0.1.dev0.dist-info/DESCRIPTION.rst
secretcrypt-1.0.1.dev0.dist-info/METADATA
secretcrypt-1.0.1.dev0.dist-info/RECORD
secretcrypt-1.0.1.dev0.dist-info/WHEEL
secretcrypt-1.0.1.dev0.dist-info/entry_points.txt
secretcrypt-1.0.1.dev0.dist-info/metadata.json
secretcrypt-1.0.1.dev0.dist-info/top_level.txt
