Metadata-Version: 2.0
Name: secretcrypt
Version: 1.0.1.dev0
Summary: Encrypt project secrets
Home-page: https://github.com/Zemanta/secretcrypt
Author: Nejc Saje, Zemanta
Author-email: nejc@saje.info
License: UNKNOWN
Download-URL: https://github.com/Zemanta/secretcrypt/tarball/0.1
Keywords: secret,encrypt,decrypt,settings
Platform: UNKNOWN
Classifier: Development Status :: 5 - Production/Stable
Classifier: Intended Audience :: Developers
Classifier: License :: OSI Approved :: Apache Software License
Classifier: Programming Language :: Python :: 2.7
Classifier: Programming Language :: Python :: 3.4
Classifier: Topic :: Security :: Cryptography
Requires-Dist: docopt (>=0.6.2)
Requires-Dist: six (>=1.10.0)
Requires-Dist: boto3 (>=1.4)
Requires-Dist: pyaes (>=1.6.0)
Requires-Dist: pyscrypt (>=1.6.2)
